{
    "id": 139048156,
    "name": "consstel never altj",
    "author": "zVixxqq",
    "creators": [],
    "verifier": "consstel",
    "verification": "https://youtu.be/OdLS3ZXX2fI?si=CHHpS9f1DpHiOwP7",
    "percentToQualify": "100",
    "handcam": "Not Required",
    "fps": "60",
    "records": [
        {
          "user": "vny8",
            "link": "https://discord.com/channels/1482610459302559838/1482642581685928128/1507423720841547796",
            "hz": "60",
            "percent": 100
        },
        {
            "user": "LightningGD",
            "link": "",
            "percent": 100,
            "hz": "60"
        }
    ]
}
