
{
    "id": 132564797,
    "name": "For The Notorious B",
    "author": "delgado_yeet_404",
    "creators": [],
    "verifier": "delgado_yeet_404",
    "verification": "https://youtu.be/JpkzMWYya7k?si=XdCehkoVBZeHYWgA",
    "percentToQualify": "100",
    "handcam": "Required",
    "fps": "CBF",
    "records": [
        {
            "user": "Liknod",
            "link": "",
            "percent": 100,
            "hz": "CBF"
        },
        {
            "user": "ywuChaos",
            "link": "",
            "percent": 100,
            "hz": "CBF"
        },
        {
            "user": "vny8",
            "link": "",
            "percent": 100,
            "hz": "CBF"
        },
        {
           "user": "AngoPR",   
           "link": "https://www.youtube.com/watch?v=Bta42NcBwfo",     
           "hz": "CBF",     
           "percent": 100
        },
        {
           "user": "G1rcy",   
           "link": "https://www.youtube.com/watch?v=cPqYed6n5mw",     
           "hz": "CBF",     
           "percent": 100
        },
        {
          "user": "JustAnUnknown",
            "link": "https://www.youtube.com/watch?v=nNYNeYIKGG8",
            "hz": "CBF",
            "percent": 100
        }
    ]
}
